[
  {
    "task": "В каком году проходило сражение на танке Ис-3",
    "answers": [
      "Вариант ответа 1",
      "Вариант ответа 2",
      "Вариант ответа 3",
      "Вариант ответа 4",
      "Вариант ответа 5"
    ],
    "rightAnswerIndex": 1
  },
  {
    "id": 2,
    "task": "Сколько объектов находится возле памятника",
    "answers": [
      "Вариант ответа 1",
      "Вариант ответа 2",
      "Вариант ответа 3"
    ],
    "rightAnswerIndex": 2
  },
  {
    "id": 3,
    "videoUrl": "https://www.youtube.com/embed/eenJpcGR0Jc",
    "answers": [
      "Вариант ответа 1",
      "Вариант ответа 2",
      "Вариант ответа 3",
      "Вариант ответа 4"
    ],
    "rightAnswerIndex": 3
  }
]
